MANIFEST.in
README.rst
bootstrap-buildout.py
buildout.cfg
requirements.txt
setup.py
version.txt
bob/__init__.py
bob.db.nivl.egg-info/PKG-INFO
bob.db.nivl.egg-info/SOURCES.txt
bob.db.nivl.egg-info/dependency_links.txt
bob.db.nivl.egg-info/entry_points.txt
bob.db.nivl.egg-info/namespace_packages.txt
bob.db.nivl.egg-info/not-zip-safe
bob.db.nivl.egg-info/requires.txt
bob.db.nivl.egg-info/top_level.txt
bob/db/__init__.py
bob/db/nivl/__init__.py
bob/db/nivl/create.py
bob/db/nivl/driver.py
bob/db/nivl/models.py
bob/db/nivl/query.py
bob/db/nivl/test.py
bob/db/nivl/utils.py
bob/db/nivl/scripts/__init__.py
bob/db/nivl/scripts/overlapped_score_distributions.py
doc/conf.py
doc/guide.rst
doc/index.rst
doc/py_api.rst